{
  "verdict": {
    "headline": "Current public sample does not yet confirm a financially viable edge.",
    "detail": "The Exchange-side sample averages +0.12% at +1h, but -0.52% at +6h and -1.49% at +24h. After netting entry quality versus market, mean net +24h drops to -2.19%. The keeper-proxy sample is weaker still at -5.59% mean +24h. That is not enough to claim the Stability Pool reliably buys bottoms profitably."
  },
  "exchange": {
    "all": {
      "count": 13,
      "execution_vs_market_pct": {
        "mean": 0.699254948643448,
        "median": 0.753006555695479,
        "count": 13
      },
      "1h_return_pct": {
        "mean": 0.1196861137382949,
        "median": 0.4865399388889413,
        "count": 13
      },
      "6h_return_pct": {
        "mean": -0.5205013662524614,
        "median": -0.002447254382298425,
        "count": 13
      },
      "24h_return_pct": {
        "mean": -1.489599202408276,
        "median": -2.406449588234394,
        "count": 13
      },
      "net_1h_return_pct": {
        "mean": -0.5795688349051531,
        "median": -0.4801940559099993,
        "count": 13
      },
      "net_6h_return_pct": {
        "mean": -1.2197563148959094,
        "median": -0.0012321298472950382,
        "count": 13
      },
      "net_24h_return_pct": {
        "mean": -2.188854151051724,
        "median": -1.4222538733593582,
        "count": 13
      }
    },
    "better_or_equal_fill": {
      "count": 5,
      "execution_vs_market_pct": {
        "mean": -0.4854026717192417,
        "median": -0.2952408317052124,
        "count": 5
      },
      "1h_return_pct": {
        "mean": -0.06234276509075043,
        "median": 0.4865399388889413,
        "count": 5
      },
      "6h_return_pct": {
        "mean": 0.22059328267894474,
        "median": -0.002447254382298425,
        "count": 5
      },
      "24h_return_pct": {
        "mean": -0.6383077792060354,
        "median": -1.4862389438342727,
        "count": 5
      },
      "net_1h_return_pct": {
        "mean": 0.42305990662849124,
        "median": 0.4877550634239447,
        "count": 5
      },
      "net_6h_return_pct": {
        "mean": 0.7059959543981864,
        "median": -0.0012321298472950382,
        "count": 5
      },
      "net_24h_return_pct": {
        "mean": -0.15290510748679376,
        "median": -0.5310288253090212,
        "count": 5
      }
    },
    "worse_fill": {
      "count": 8,
      "execution_vs_market_pct": {
        "mean": 1.439665961370129,
        "median": 1.194105514344157,
        "count": 8
      },
      "1h_return_pct": {
        "mean": 0.23345416300644822,
        "median": 0.25983069155626204,
        "count": 8
      },
      "6h_return_pct": {
        "mean": -0.9836855218345901,
        "median": 0.02378178589075297,
        "count": 8
      },
      "24h_return_pct": {
        "mean": -2.0216563419096762,
        "median": -2.673353339863377,
        "count": 8
      },
      "net_1h_return_pct": {
        "mean": -1.2062117983636809,
        "median": -1.1912760277072554,
        "count": 8
      },
      "net_6h_return_pct": {
        "mean": -2.423351483204719,
        "median": -0.8471964406699062,
        "count": 8
      },
      "net_24h_return_pct": {
        "mean": -3.4613223032798057,
        "median": -3.9962631821116315,
        "count": 8
      }
    },
    "large_ge_1000": {
      "count": 5,
      "execution_vs_market_pct": {
        "mean": 1.440070921710448,
        "median": 1.3883555896657906,
        "count": 5
      },
      "1h_return_pct": {
        "mean": 0.022215306900423837,
        "median": 0.0,
        "count": 5
      },
      "6h_return_pct": {
        "mean": -1.997778883403436,
        "median": -1.5109541647676417,
        "count": 5
      },
      "24h_return_pct": {
        "mean": -0.9972345953625927,
        "median": -0.018495404834861784,
        "count": 5
      },
      "net_1h_return_pct": {
        "mean": -1.417855614810024,
        "median": -2.037314562935344,
        "count": 5
      },
      "net_6h_return_pct": {
        "mean": -3.437849805113884,
        "median": -2.8993097544334323,
        "count": 5
      },
      "net_24h_return_pct": {
        "mean": -2.4373055170730407,
        "median": -0.6238929009198535,
        "count": 5
      }
    },
    "small_lt_1000": {
      "count": 8,
      "execution_vs_market_pct": {
        "mean": 0.23624496547657303,
        "median": 0.3758957155802378,
        "count": 8
      },
      "1h_return_pct": {
        "mean": 0.1806053680119643,
        "median": 0.5031006610007327,
        "count": 8
      },
      "6h_return_pct": {
        "mean": 0.40279708196689773,
        "median": 0.8159413897654177,
        "count": 8
      },
      "24h_return_pct": {
        "mean": -1.797327081811828,
        "median": -2.4341106929030465,
        "count": 8
      },
      "net_1h_return_pct": {
        "mean": -0.055639597464608725,
        "median": -0.3877377018841499,
        "count": 8
      },
      "net_6h_return_pct": {
        "mean": 0.1665521164903247,
        "median": 0.0622525897947479,
        "count": 8
      },
      "net_24h_return_pct": {
        "mean": -2.033572047288401,
        "median": -2.2713463141506574,
        "count": 8
      }
    },
    "largest_cases": [
      {
        "start_utc": "2026-03-27T08:35:55+00:00",
        "end_utc": "2026-03-27T08:36:15+00:00",
        "tx_count": 25,
        "hyusd_burned": 17968.306560999998,
        "xsol_minted": 243241.57956299998,
        "implied_hyusd_per_xsol": 0.07387020999157003,
        "market_entry_close": 0.07269814442650883,
        "execution_vs_market_pct": 1.6122358752169275,
        "sample_signature": "4TJBHLfubdJ1QP52jKrPTHqDqEaLdPZy4qAWceQbFLKbE8x5RXDtg2JkM1w3V9QYLBhuZxvAB5ZFJXgdcpyXntfY",
        "signatures": [
          "4TJBHLfubdJ1QP52jKrPTHqDqEaLdPZy4qAWceQbFLKbE8x5RXDtg2JkM1w3V9QYLBhuZxvAB5ZFJXgdcpyXntfY",
          "6433zd2F2HcSnGo1JJrNUEoKmpDfW7gdmiJfvaVziL2k4Pq8k2Kqx6XPSC4FqApAgR9roSG4ajMAzQ3oFwTz3R5g",
          "uQ8Zqgb6fs4XB2y6zMeBsTwke8XN6JDv41jTcXNZNEnkg3DsW56gb24KtC8moMkqMhapT168nPHYw1ocagurKGS",
          "2uviLV5JLUgrDzdQmftCgRUEJx7RNugLYHPgK7FW2rDxnjajdXDA6rCUtAKDr4p5tGVEh9gMVXscFcDHBwssSGAZ",
          "4WPMv5tzimLuigbq4LX9UJSGxBM2Yv61v3ja6hMXwFHeWUUkrbWmeuxJccoJfe9x5jtPmqafvJ8xdrEx2122yK3V",
          "3VuEgFoJyyHfx5tqLsGAExydFBo3JnCddpJW3WrU9JccYanDZTcwyHjQJhRDhyrcUJTuJBHK2tN1SzyEiwANQbay",
          "5W8uzNGoy9ucEtCneEj5sJ5M7HoBCPhbrkbMCmQ8tzEq6VALvv9PHM8fChpkvTLyhYKBeci8YX5KEZcXxm5g2a8v",
          "2hSYwWH2WUggqQk1K6RY2zDgzCB21z9bWGGNJeCmqcV6JvwF6XGZz7TRBtx9wyyXdeXCBhMcUnpP4qz8teJhxTXW",
          "3SKgYhQ8D6TJgSotGiwKJktH1fkTK8CUfN1XK7ePGPBuPTFrArNoios99KwETwkKT4zQZKfqxz7ni7EmdLtms3RX",
          "wXVARD7J8EhN3C2PL15ma7myDXtJ2ok4Mfo45PheAkfU4sz3hauhx6i8pJWiFRdYDTKVXZXfNED1zWSv4YxJ8wS",
          "ycTjr6niFTceYNsLcjrf9KcHBNAhNwF6o1k4XwWS5WLAVsAWLGdREv6sb4DJrWtrG5rzgpnJejsv3G9i55vp6HK",
          "4Qhpw1uFvmcsnoKKXkVBeD1oLXUwfeSoSZyvDiU9H9bvRscKgbit5DMqjczmdWqEfvVrphiid2ewX4vBU6wrTogX",
          "E53ueAxRhQ8fXJCKkfaS9Gtuheq3X6sXN5n2ng8hrQCR2dBH4hNdFMTDt5JxhtyvcXTwJwE4XbTVWVqQSnMy2PC",
          "46JC4tvEx4hyk5UHWefzaaUw7ctXfX89HGsFDEg9sBQJZgjqiBPMHfGjtS8UCrxKrDYyBgLboEpLTz2QeivtejnR",
          "29WDDq8YCSFGsdgjKUVXzxv1bZAWGwKtT7yBUaf16VVvUFGeWFo6CtTZMKFnnBEbXDfrGbMKCrDST8T98JJDKCCN",
          "4i6EAW35VKynaLTuaFx6YXZLKsfecCvJVuH7HSNKyuFL5fdc61nSNcDBAH9WHucirRf5tDKAUR4GTNkMKXw16Trz",
          "5scGoW81RZeB65nucQQnEWacttKyHDmNe34ZonG8kUb2SRsvMegzTGLXmKN3GDEAe92o57MVTAYD1FQh2dAiB1ph",
          "5NkgtnWw9hiweqSHLAgvHJX4ecYvzuJ7LkJ59jhHkKo1oRBMX4LPdcaWNz46DKR7vvQPjrs2hteM8AUzBzCBBSmy",
          "2ShdYUeiLnv4CPeQwVgWLRbBNwEgzFFWGuDGSncFpE2MqsHqRhMHBXgPasXL4k188z2yvscv58RzG6sV8H59YKr9",
          "4XmabjfhFY5j7NmYrtQasj2tSbx1rzQVfiuBRP1pNP8D3J5LvTMYLG2oaci6YG95HLkGQ57mpGCt2FKPHnyh5hEV",
          "DoJi1yLmVETgneYNujFfqKWA2dmp6skAGm1rvL1BREqdjLt4hgqepRgEUUCNqfuMEesu9sreBPhhmc2Y6G8fjW9",
          "2gm8PJkepARiX4YAA9axfpuV7ZYs23Gon3hFVxHkkuy9kkNDxRgPrbq415r8c3R3rLXkBK1nNGLTtA23WHZQAsRq",
          "3fMtN9PqctNcAt7D4DihQcFtYMmaGD185ogu3HAuqFUjtQuLXS49whT7C5frdhDxxQvZh8exNdU6k2h4fvmJFSaJ",
          "4nQVr3qMCVLVb5KkmznDvSjpS6MdoPx1kDWS5vwhAdgHdwrzHVJj4YPNa5dpD6z68HX5YqfBze1txKq6MpmyVmfP",
          "2E1m9yzzYZvaY8yEkU7oSdqUfGjJYnzJivCWEKknfxHyRijQ43A5zkj17BEi4Jjz244VwH3XGbzCjU9wTnZzT4HZ"
        ],
        "1h_return_pct": -0.4250786877184165,
        "6h_return_pct": -10.323719075376935,
        "24h_return_pct": -7.134937970063593,
        "net_1h_return_pct": -2.037314562935344,
        "net_6h_return_pct": -11.935954950593864,
        "net_24h_return_pct": -8.747173845280521
      },
      {
        "start_utc": "2026-03-27T10:37:32+00:00",
        "end_utc": "2026-03-27T10:37:59+00:00",
        "tx_count": 22,
        "hyusd_burned": 4712.858749,
        "xsol_minted": 67972.15321199999,
        "implied_hyusd_per_xsol": 0.06933513985206488,
        "market_entry_close": 0.06680618039162692,
        "execution_vs_market_pct": 3.785517216540235,
        "sample_signature": "3qi3aWcbjFqmiMrWUeW8egLrLutURSbjRQUPTDDbqedqhwA4he5qU9mUDNVVAQCuGi4PJiqkm6o9pw7K54N1QmVE",
        "signatures": [
          "3qi3aWcbjFqmiMrWUeW8egLrLutURSbjRQUPTDDbqedqhwA4he5qU9mUDNVVAQCuGi4PJiqkm6o9pw7K54N1QmVE",
          "2yMJuWYiRUqM6489GS4KTCoG9DX2oSjYGyHG8ES6wwCkdJMuekJgj4Eebvn1kC94BKuWAcJjWRrKRbA5kdSS6i4b",
          "E3KFDjRx2xDEkXyVqVFw9ZPTUsq6W7dXNCgwkFp4SeXpQq3T5oCHoz8x7PAqsYQhCuhVPKdt5HeCyrcLEWahwFS",
          "2SZqbNZc53k7KrG6X8Bgohie9AhNNxwsUK2bVCP43rFZKrMCwwbmQEphPkBFoFcQWzxuMAUoycWiTNMKTvKjrVwQ",
          "7bYz4mQmpCaJZiMBg9QnhpB3ikFTeR6xvA1SADZAyoG3unZJgjrQ67tpCBrSpjK8ctHF2aRAoEhh3yE2maK4738",
          "kZNxWvQ1YdCzE9m2thp6ZFu2LYE6haFbhRKTybb9Reyh9h2CkVytpikpVcTKsNe2fPCLupmuafv6JCoWMhiCYbx",
          "34u4eC9naDo3RwGfyEBQGPfw5hSGkKs92fkrdBjJqjeB63JtVBrWC5LKoefKC2xxXtk7eUiPRgSnBdyyoSiyaLDR",
          "2VtujKxJ5TGaX83BwejQiZJR8qVoM6VsZjArJsjJTnKFEJbnmU1KkCWdAG46x8PmiatMSh84TBxfBPz8RDh3AJK6",
          "PCHjRkKdzYYCz2wTuGHzepxoDeafKRu4MMSW8MdiKdRs5UrJkGRsqbT2rmU2vaHpJHjXMGsvY1GBa5ACRK2JMMz",
          "4LMHaAuzQge2mtyFrXyjtTPufSfhgJukJ5KSa2h5NUAKzcrCBQmESd7KeWjkVydWkrJhx39d5yf3hwb14RE2Wdfc",
          "61tykp9M7h6TxWCG8QpY4XSU1kCPb6ewbUMYCP4PydKvqJnhmCRN1zRBNVygCziYPGmXt3jKHGUoWBn5gzCYBKwX",
          "4fjZk97VihDcifEeyuFcvJscKFhs18GxJKEcL9RSJGeKTCq2QfWZvCqxk3ud275xCG2592UiUQytNCGBZ4ifzTSJ",
          "5fKRybuKuQfTmqJMwsqb4G2dLLkH5RsZNxLqnHGLG49kBsc1dGaNkpijRCFAQzFuunE6KzNbN7dAyAj6jxvpKC4s",
          "36CQauJg59gfMPfZPUtoaWpYV1MbLshqNjAbJGDD751QuiteutvSdwW5zioJquhgDVYyPK9ZjHYFAaLiYxBukpJX",
          "4JMGmajEzBg33wmBHYks6cUd4ukySETHU7mtWjjcMnhrwavJWVnqNHSS9bngM8uEjzqmx3NhBUNJ9SXnp7kE97Av",
          "eVTD4xcVq5uF5eu4sRS9LNw2gwDzGXFSeafA4yHJt7gdRx1ZwzEpawKfnyXtkFeUpqj6MqxFAu1pSg2qix4xMSa",
          "5RCjj5C3kk4U8ryc2inGZ8HDgFLNt2CfgxbYSUkRpeC8TjGZBbcTqkQZXPQSpv82mDmCFwAmZ5yZ4EVNbnmoMFi2",
          "54FUSPpppVH1iAUDahDsoiKAJvQSJ4cXD3STVG3ShMLMJXNHbGrZTtxj3qWso7GW3a8NT2pRbjRC6p3zjY9SPx3L",
          "JMZEBLWdUbFnW5Hp6mt6Nm4k2iebStzS5WupAy8Tv7Mda87d8HCMKjSxXWFdyGb5CBokC1EBRxLLqZaaMFwptNg",
          "4WykUdtANxbDwhPv7Cjk1TwKvrK2jQNv311qaRp144wjTPTCA1gaEM2cyKPCejVpVaTLdLXUPQ3zQQGqDFNEJ7h6",
          "3pFGYxfVZ6GWAdDPaaA8d4qr2rrogbUdDx4xcVjEgCWZcMqJPvcqUTBsesLk5zQYFgF398QSMpFmGzBCm9QjxJPF",
          "46JagfRVt4ycZHWPd33WrbzksRiGQPzYj8yztLSMEf2n4Fg4X4FfiooVxB7J9aAC83A1v8Uhhm5Rfmvt1BUDu8Hr"
        ],
        "1h_return_pct": 1.3929484080949628,
        "6h_return_pct": -4.316358300658996,
        "24h_return_pct": -2.8849348821550547,
        "net_1h_return_pct": -2.3925688084452723,
        "net_6h_return_pct": -8.10187551719923,
        "net_24h_return_pct": -6.670452098695289
      },
      {
        "start_utc": "2026-03-27T22:42:37+00:00",
        "end_utc": "2026-03-27T22:42:37+00:00",
        "tx_count": 1,
        "hyusd_burned": 4534.991158,
        "xsol_minted": 69827.65220699999,
        "implied_hyusd_per_xsol": 0.06494549100056068,
        "market_entry_close": 0.06455467859275443,
        "execution_vs_market_pct": 0.6053974960849917,
        "sample_signature": "2zeYQJMaswq9XVD4va8VkV56p933CY91BMcmBXWxSW8knoVdy3AVXdRE3jyaYWfyrNoQdTY7z65o72UQyZvKg981",
        "signatures": [
          "2zeYQJMaswq9XVD4va8VkV56p933CY91BMcmBXWxSW8knoVdy3AVXdRE3jyaYWfyrNoQdTY7z65o72UQyZvKg981"
        ],
        "1h_return_pct": 0.0,
        "6h_return_pct": 1.0033269682993673,
        "24h_return_pct": -0.018495404834861784,
        "net_1h_return_pct": -0.6053974960849917,
        "net_6h_return_pct": 0.3979294722143756,
        "net_24h_return_pct": -0.6238929009198535
      },
      {
        "start_utc": "2026-03-27T13:49:50+00:00",
        "end_utc": "2026-03-27T13:56:44+00:00",
        "tx_count": 4,
        "hyusd_burned": 2315.4499379999997,
        "xsol_minted": 34684.884857,
        "implied_hyusd_per_xsol": 0.06675674281596189,
        "market_entry_close": 0.06584261321500928,
        "execution_vs_market_pct": 1.3883555896657906,
        "sample_signature": "2pkZnuxX54zX9VVcx2GXHSTfDWGhe1gGYivvKSTi1aDzzzF6hPjKXqdMo9h6vo6Xm8aLQNiZNeneRJJpFvUGDzqx",
        "signatures": [
          "2pkZnuxX54zX9VVcx2GXHSTfDWGhe1gGYivvKSTi1aDzzzF6hPjKXqdMo9h6vo6Xm8aLQNiZNeneRJJpFvUGDzqx",
          "M81pJrju6zUBJ6mDi69xUo1bWFqQKf2UZRqGmZM2nfGq9dLdD7aiZMyMwi7KcRW7PCqsrPNiUreShizLhq7Svty",
          "4gXU1w7kNQjSDQQzVzSATmSTrShJKSom6pUB9bSqMHU714EZdRbvMXYwoh54QKtq6hR84d5rMJuSK8WrP84mLE9C",
          "5tE5gaGvn5fFFAt5t2deeYupuPwqCFxc5jxSWVucM8TRQ3hRakDCgbFvqUQWoKrZpTVfhZWeNLxY9r6RLFTvktxP"
        ],
        "1h_return_pct": -1.869293569695174,
        "6h_return_pct": -1.5109541647676417,
        "24h_return_pct": 1.4352023025073102,
        "net_1h_return_pct": -3.2576491593609647,
        "net_6h_return_pct": -2.8993097544334323,
        "net_24h_return_pct": 0.04684671284151953
      },
      {
        "start_utc": "2026-03-27T18:24:43+00:00",
        "end_utc": "2026-03-27T18:25:26+00:00",
        "tx_count": 13,
        "hyusd_burned": 1338.675046,
        "xsol_minted": 21306.233276,
        "implied_hyusd_per_xsol": 0.06283020694736902,
        "market_entry_close": 0.06295053788820838,
        "execution_vs_market_pct": -0.1911515689557053,
        "sample_signature": "cS47L8FhL6W7g7p4c9gFkm6hSxEo9om2XgTeqGd3uNHaDZiRiaNi6CRbQ4KcLbD5YhQN6XhpreNXiaNNYbAgNTC",
        "signatures": [
          "cS47L8FhL6W7g7p4c9gFkm6hSxEo9om2XgTeqGd3uNHaDZiRiaNi6CRbQ4KcLbD5YhQN6XhpreNXiaNNYbAgNTC",
          "xJ4Fcima7gKmSsH9HKZUnbDANdnzVxTiYdBmnFc3Vp5XRhvQsbR5EFDfvy1Gfzb4sqWuuTCAvb87brQibkUtpyo",
          "bcsCiXhHiiBmswtgFBzo8dcDpnKySSJpU9LrHjQRRMcSdT5FEAsBqyyzi5r9doaoWsgktXyc7A86kNE6s3K7tsy",
          "4aZVEJfYWNPmnjRF5Jm2XHCKUYtjTreAoMPXNpo4yXiExfSchwkY7uEdnBN231wwGoQYCbCuUCLUuCQiq51JsfDQ",
          "2y8kuCfsETuQtzxoZ6Qbd2rfkinwtnR8g2GfuHpWCb6JxWh4c8tvHa5j49sps9eD5V9hSZmSdJcHUQ7RvyL2h3mK",
          "4GRabhS1AeHNkpZ98pSkgHKb9B31Csjczr6VEqZLFjCh4TmZ2gQMpSZVp4f5tmtiDhHmfogKTLqwRR4k995bdNJ1",
          "4c8n7pC74FkrrsexHTBRayqpwucpz5BVRE7h8dS7MSqeR1cSksoVP8ykphxM2ZnpLDwqWxgY35TKU1VfLWmFcnU1",
          "2xi4TD56iqxD2enMTDaQeT3mWQzYJST7zbyjPSpoR1gPSRR4bB7iQ5Pp5wm8TCLsgEqh6vmNzWxvbUwpKfV7xL2f",
          "5M62TB9SgtrDDPjKAHe9iPeKNe4R9uR1jgW3SNMmZQssJ2AGDhGi3nTjC9RhGTYPkYpVKg7KfNoAfJVS3wEE8KTU",
          "CJ7qB8emQjbT9pmWKvf3JzpmLVebhaVSY5pT328vyTnF6c6bCMQ75shzkhN6S4Gj1GY6VsumzhCMEVmouKe5DAP",
          "66cobzszzE9Rjdsi4GN7pVFRxqDRbWXKUWP3efmbV4WaqkyPzJTYNTL8cBthmEkSnkrJwmGcmgVqpqkysk1E2Nni",
          "3k4ni8FKMBybcmHRPD7WJpoTQV9q2AfwrffsmfUxzfkr7fV7HG9xrsTTJNpa4kEyJYijsCLHmeZR4Hn7ocWVyzMQ",
          "3uc813sq2pnd3rbPB2z55tC2U921wrbpZECEF4B1bQTLsmXyGkLX56igysvdpWwLGx2vXJSLj1ecya7eV42yxQwH"
        ],
        "1h_return_pct": 1.012500383820747,
        "6h_return_pct": 5.158810155487026,
        "24h_return_pct": 3.6169929777332355,
        "net_1h_return_pct": 1.2036519527764522,
        "net_6h_return_pct": 5.349961724442731,
        "net_24h_return_pct": 3.8081445466889408
      },
      {
        "start_utc": "2026-03-28T11:43:39+00:00",
        "end_utc": "2026-03-28T11:51:33+00:00",
        "tx_count": 2,
        "hyusd_burned": 769.8992309999999,
        "xsol_minted": 11634.971040999999,
        "implied_hyusd_per_xsol": 0.06617113427158379,
        "market_entry_close": 0.06551606829925993,
        "execution_vs_market_pct": 0.9998554390225234,
        "sample_signature": "2B5pKWGDLKdxJScsTxmKt1FEYznqzT5vox3zqdzjXPa7P13kwCwDexvhNvDkYUgJjgL6b5N6V2HbwE1tTGTFWdCB",
        "signatures": [
          "2B5pKWGDLKdxJScsTxmKt1FEYznqzT5vox3zqdzjXPa7P13kwCwDexvhNvDkYUgJjgL6b5N6V2HbwE1tTGTFWdCB",
          "5G6fbZh6agMssYsv4VAXuYxmB4Go16M6GBUEpUgzNrbe4m2sjcHqwMxTwh1Dn9DqP5mTWZexABKwXfeTv6khydPV"
        ],
        "1h_return_pct": 0.5196613831125241,
        "6h_return_pct": 3.037224060577959,
        "24h_return_pct": -3.8889031448018363,
        "net_1h_return_pct": -0.4801940559099993,
        "net_6h_return_pct": 2.0373686215554354,
        "net_24h_return_pct": -4.88875858382436
      },
      {
        "start_utc": "2026-03-28T04:20:24+00:00",
        "end_utc": "2026-03-28T04:20:24+00:00",
        "tx_count": 1,
        "hyusd_burned": 561.440713,
        "xsol_minted": 8653.569851,
        "implied_hyusd_per_xsol": 0.06487966500150459,
        "market_entry_close": 0.06488045337981203,
        "execution_vs_market_pct": -0.0012151245350033868,
        "sample_signature": "4HwKCEz7jSrBY1cqGL482puDFcveP4ieonMNR9zhKKJ7jNViyfKP1xH3WbWpE5L8myqnfnn7AvLiJXZ4Ry916FB1",
        "signatures": [
          "4HwKCEz7jSrBY1cqGL482puDFcveP4ieonMNR9zhKKJ7jNViyfKP1xH3WbWpE5L8myqnfnn7AvLiJXZ4Ry916FB1"
        ],
        "1h_return_pct": 0.4865399388889413,
        "6h_return_pct": -0.002447254382298425,
        "24h_return_pct": 0.49983624495242296,
        "net_1h_return_pct": 0.4877550634239447,
        "net_6h_return_pct": -0.0012321298472950382,
        "net_24h_return_pct": 0.5010513694874263
      },
      {
        "start_utc": "2026-03-28T01:36:37+00:00",
        "end_utc": "2026-03-28T01:50:22+00:00",
        "tx_count": 4,
        "hyusd_burned": 415.23196499999995,
        "xsol_minted": 6416.653170999999,
        "implied_hyusd_per_xsol": 0.06471161116774034,
        "market_entry_close": 0.06422797034048633,
        "execution_vs_market_pct": 0.753006555695479,
        "sample_signature": "4ZPU1xxJRMC9NjBKW19MRgQKz84BKsL11NTeCDsfuMy2gUdpUnnAKuMit2KwmzScUqfLbFCXcGR3pbtPTUVtyYJ",
        "signatures": [
          "4ZPU1xxJRMC9NjBKW19MRgQKz84BKsL11NTeCDsfuMy2gUdpUnnAKuMit2KwmzScUqfLbFCXcGR3pbtPTUVtyYJ",
          "63eeiEi4HMWRnh9dNfU5opPrF2LDfcDayDkEQ3EaZXhfPzXzTsJeo2zQaR2RP86QHXVwNTDoDC4o4NFUfNC24Qms",
          "QnH8pQ6rw5XbTEJPNaDRNYKcDvqsNXoYWJzJCDfmijpqV1u9VThpv77t1Vw79Y4HqBjUkaVZhKmQEMMFfD9zoKM",
          "4QBU83cR7TyZzU5MsRYswwRbgFUGynEJ7jZmByze1KCA2EVV5z23cZdsr7n2Vm2DtQibE1PZ9DJVBt7j3Fyydf1A"
        ],
        "1h_return_pct": 2.021338950445628,
        "6h_return_pct": 3.5624296998542526,
        "24h_return_pct": -2.461771797571699,
        "net_1h_return_pct": 1.268332394750149,
        "net_6h_return_pct": 2.8094231441587736,
        "net_24h_return_pct": -3.214778353267178
      }
    ]
  },
  "keeper": {
    "all": {
      "count": 34,
      "1h_return_pct": {
        "mean": -0.4525485374574021,
        "median": -0.6876956733607886,
        "count": 34
      },
      "6h_return_pct": {
        "mean": -1.7587528789979505,
        "median": -0.9791813773417757,
        "count": 29
      },
      "24h_return_pct": {
        "mean": -5.585390778903872,
        "median": -4.396641306806326,
        "count": 25
      }
    }
  }
}